aliyunsdkoceanbasepro/__init__.py
aliyunsdkoceanbasepro/endpoint.py
aliyunsdkoceanbasepro/request/__init__.py
aliyunsdkoceanbasepro/request/v20190901/BatchKillProcessListRequest.py
aliyunsdkoceanbasepro/request/v20190901/BatchKillSessionListRequest.py
aliyunsdkoceanbasepro/request/v20190901/CancelProjectModifyRecordRequest.py
aliyunsdkoceanbasepro/request/v20190901/CreateBackupSetDownloadLinkRequest.py
aliyunsdkoceanbasepro/request/v20190901/CreateDatabaseRequest.py
aliyunsdkoceanbasepro/request/v20190901/CreateInstanceRequest.py
aliyunsdkoceanbasepro/request/v20190901/CreateLabelRequest.py
aliyunsdkoceanbasepro/request/v20190901/CreateMySqlDataSourceRequest.py
aliyunsdkoceanbasepro/request/v20190901/CreateOasOutlineTaskRequest.py
aliyunsdkoceanbasepro/request/v20190901/CreateOceanBaseDataSourceRequest.py
aliyunsdkoceanbasepro/request/v20190901/CreateOmsMysqlDataSourceRequest.py
aliyunsdkoceanbasepro/request/v20190901/CreateProjectModifyRecordsRequest.py
aliyunsdkoceanbasepro/request/v20190901/CreateProjectRequest.py
aliyunsdkoceanbasepro/request/v20190901/CreateRdsPostgreSQLDataSourceRequest.py
aliyunsdkoceanbasepro/request/v20190901/CreateSecurityIpGroupRequest.py
aliyunsdkoceanbasepro/request/v20190901/CreateTagRequest.py
aliyunsdkoceanbasepro/request/v20190901/CreateTagValueRequest.py
aliyunsdkoceanbasepro/request/v20190901/CreateTenantReadOnlyConnectionRequest.py
aliyunsdkoceanbasepro/request/v20190901/CreateTenantRequest.py
aliyunsdkoceanbasepro/request/v20190901/CreateTenantSecurityIpGroupRequest.py
aliyunsdkoceanbasepro/request/v20190901/CreateTenantUserRequest.py
aliyunsdkoceanbasepro/request/v20190901/DeleteDataSourceRequest.py
aliyunsdkoceanbasepro/request/v20190901/DeleteDatabasesRequest.py
aliyunsdkoceanbasepro/request/v20190901/DeleteInstancesRequest.py
aliyunsdkoceanbasepro/request/v20190901/DeleteProjectRequest.py
aliyunsdkoceanbasepro/request/v20190901/DeleteSecurityIpGroupRequest.py
aliyunsdkoceanbasepro/request/v20190901/DeleteTagRequest.py
aliyun_python_sdk_oceanbasepro-1.0.31.dist-info/LICENSE
aliyun_python_sdk_oceanbasepro-1.0.31.dist-info/METADATA
aliyun_python_sdk_oceanbasepro-1.0.31.dist-info/WHEEL
aliyun_python_sdk_oceanbasepro-1.0.31.dist-info/top_level.txt
aliyun_python_sdk_oceanbasepro-1.0.31.dist-info/RECORD
